{
    "Similarity Threshold": [
        0.75
    ],
    "Ground User Coverage threshold": [
        0,
        0.2,
        0.4,
        0.8,
        1
    ],
    "Number of Users": [
        50,
        100,
        150,
        200,
        250
    ],
    "Area Size": [
        "20 20",
        "50 50",
        "100 100",
        "150 150"
    ],
    "UAV Communication Radius": [
        4,
        8,
        12,
        16,
        20
    ],
    "plot_name": "UAV vs Number of Users",
    "x_axis": "Number of Users",
    "y_axis": "Number of UAV"
}
